bananaproto/__init__.py
bananaproto/_types.py
bananaproto/casing.py
bananaproto/compile/__init__.py
bananaproto/compile/importing.py
bananaproto/compile/naming.py
bananaproto/event_loop.py
bananaproto/grpc/__init__.py
bananaproto/grpc/grpclib_client.py
bananaproto/grpc/grpclib_server.py
bananaproto/grpc/util/__init__.py
bananaproto/grpc/util/async_channel.py
bananaproto/lib/__init__.py
bananaproto/lib/google/__init__.py
bananaproto/lib/google/protobuf/__init__.py
bananaproto/lib/google/protobuf/compiler/__init__.py
bananaproto/plugin/__init__.py
bananaproto/plugin/__main__.py
bananaproto/plugin/compiler.py
bananaproto/plugin/main.py
bananaproto/plugin/models.py
bananaproto/plugin/parser.py
bananaproto/plugin/plugin.bat
bananaproto/py.typed
bananaproto/templates/template.py.j2
bananaproto-1.3.0.dist-info/entry_points.txt
bananaproto-1.3.0.dist-info/METADATA
bananaproto-1.3.0.dist-info/WHEEL
bananaproto-1.3.0.dist-info/RECORD
