Metadata-Version: 2.1
Name: bananaproto
Version: 1.3.0
Summary: A BANANA Protobuf / gRPC generator & library
Home-page: https://github.com/BananaLoaf/python-bananaproto
License: MIT
Keywords: protobuf,gRPC
Author: Daniel G. Taylor
Author-email: danielgtaylor@gmail.com
Maintainer: BananaLoaf
Maintainer-email: bananaloaf@protonmail.com
Requires-Python: >=3.10,<4.0
Classifier: License :: OSI Approved :: MIT License
Classifier: Programming Language :: Python :: 3
Classifier: Programming Language :: Python :: 3.10
Classifier: Programming Language :: Python :: 3.11
Provides-Extra: compiler
Requires-Dist: black (>=19.3b0) ; extra == "compiler"
Requires-Dist: grpclib (>=0.4.1,<0.5.0)
Requires-Dist: isort (>=5.11.5,<6.0.0) ; extra == "compiler"
Requires-Dist: jinja2 (>=3.0.3) ; extra == "compiler"
Requires-Dist: python-dateutil (>=2.8,<3.0)
Requires-Dist: python-singleton (>=0.1.2,<0.2.0)
Project-URL: Repository, https://github.com/BananaLoaf/python-bananaproto
